{
  "m_GameObject": {
    "m_FileID": 0,
    "m_PathID": 4304
  },
  "m_Enabled": 1,
  "m_Script": {
    "m_FileID": 1,
    "m_PathID": 1780
  },
  "m_Name": "",
  "version": 3,
  "materialIdsValid": true,
  "needMaterialInstance": true,
  "spriteDefinitions": [
    {
      "name": "",
      "boundsData": [
        {
          "x": 31.0,
          "y": -31.0,
          "z": 0.0
        },
        {
          "x": 64.0,
          "y": 64.0,
          "z": 0.0
        }
      ],
      "untrimmedBoundsData": [
        {
          "x": 31.0,
          "y": -31.0,
          "z": 0.0
        },
        {
          "x": 64.0,
          "y": 64.0,
          "z": 0.0
        }
      ],
      "texelSize": {
        "x": 1.0,
        "y": 1.0
      },
      "positions": [
        {
          "x": -1.0,
          "y": -63.0,
          "z": 0.0
        },
        {
          "x": 63.0,
          "y": -63.0,
          "z": 0.0
        },
        {
          "x": -1.0,
          "y": 1.0,
          "z": 0.0
        },
        {
          "x": 63.0,
          "y": 1.0,
          "z": 0.0
        }
      ],
      "normals": [],
      "tangents": [],
      "uvs": [
        {
          "x": 0.0019541015,
          "y": 0.7910166
        },
        {
          "x": 0.0039052735,
          "y": 0.7910166
        },
        {
          "x": 0.0019541015,
          "y": 0.7929678
        },
        {
          "x": 0.0039052735,
          "y": 0.7929678
        }
      ],
      "normalizedUvs": [],
      "indices": [
        0,
        3,
        1,
        2,
        3,
        0
      ],
      "material": {
        "m_FileID": 0,
        "m_PathID": 85
      },
      "materialId": 0,
      "materialIndexData": [],
      "sourceTextureGUID": "",
      "extractRegion": false,
      "regionX": 0,
      "regionY": 0,
      "regionW": 0,
      "regionH": 0,
      "flipped": 0,
      "complexGeometry": false,
      "physicsEngine": 0,
      "colliderType": 0,
      "customColliders": [],
      "colliderVertices": [],
      "colliderIndicesFwd": [],
      "colliderIndicesBack": [],
      "colliderConvex": false,
      "colliderSmoothSphereCollisions": false,
      "polygonCollider2D": [],
      "edgeCollider2D": [],
      "attachPoints": []
    },
    {
      "name": "",
      "boundsData": [
        {
          "x": 31.0,
          "y": -31.0,
          "z": 0.0
        },
        {
          "x": 64.0,
          "y": 64.0,
          "z": 0.0
        }
      ],
      "untrimmedBoundsData": [
        {
          "x": 31.0,
          "y": -31.0,
          "z": 0.0
        },
        {
          "x": 64.0,
          "y": 64.0,
          "z": 0.0
        }
      ],
      "texelSize": {
        "x": 1.0,
        "y": 1.0
      },
      "positions": [
        {
          "x": -1.0,
          "y": -63.0,
          "z": 0.0
        },
        {
          "x": 63.0,
          "y": -63.0,
          "z": 0.0
        },
        {
          "x": -1.0,
          "y": 1.0,
          "z": 0.0
        },
        {
          "x": 63.0,
          "y": 1.0,
          "z": 0.0
        }
      ],
      "normals": [],
      "tangents": [],
      "uvs": [
        {
          "x": 0.0019541015,
          "y": 0.7910166
        },
        {
          "x": 0.0039052735,
          "y": 0.7910166
        },
        {
          "x": 0.0019541015,
          "y": 0.7929678
        },
        {
          "x": 0.0039052735,
          "y": 0.7929678
        }
      ],
      "normalizedUvs": [],
      "indices": [
        0,
        3,
        1,
        2,
        3,
        0
      ],
      "material": {
        "m_FileID": 0,
        "m_PathID": 85
      },
      "materialId": 0,
      "materialIndexData": [],
      "sourceTextureGUID": "",
      "extractRegion": false,
      "regionX": 0,
      "regionY": 0,
      "regionW": 0,
      "regionH": 0,
      "flipped": 0,
      "complexGeometry": false,
      "physicsEngine": 0,
      "colliderType": 0,
      "customColliders": [],
      "colliderVertices": [],
      "colliderIndicesFwd": [],
      "colliderIndicesBack": [],
      "colliderConvex": false,
      "colliderSmoothSphereCollisions": false,
      "polygonCollider2D": [],
      "edgeCollider2D": [],
      "attachPoints": []
    },
    {
      "name": "",
      "boundsData": [
        {
          "x": 31.0,
          "y": -31.0,
          "z": 0.0
        },
        {
          "x": 64.0,
          "y": 64.0,
          "z": 0.0
        }
      ],
      "untrimmedBoundsData": [
        {
          "x": 31.0,
          "y": -31.0,
          "z": 0.0
        },
        {
          "x": 64.0,
          "y": 64.0,
          "z": 0.0
        }
      ],
      "texelSize": {
        "x": 1.0,
        "y": 1.0
      },
      "positions": [
        {
          "x": -1.0,
          "y": -63.0,
          "z": 0.0
        },
        {
          "x": 63.0,
          "y": -63.0,
          "z": 0.0
        },
        {
          "x": -1.0,
          "y": 1.0,
          "z": 0.0
        },
        {
          "x": 63.0,
          "y": 1.0,
          "z": 0.0
        }
      ],
      "normals": [],
      "tangents": [],
      "uvs": [
        {
          "x": 0.0019541015,
          "y": 0.7910166
        },
        {
          "x": 0.0039052735,
          "y": 0.7910166
        },
        {
          "x": 0.0019541015,
          "y": 0.7929678
        },
        {
          "x": 0.0039052735,
          "y": 0.7929678
        }
      ],
      "normalizedUvs": [],
      "indices": [
        0,
        3,
        1,
        2,
        3,
        0
      ],
      "material": {
        "m_FileID": 0,
        "m_PathID": 85
      },
      "materialId": 0,
      "materialIndexData": [],
      "sourceTextureGUID": "",
      "extractRegion": false,
      "regionX": 0,
      "regionY": 0,
      "regionW": 0,
      "regionH": 0,
      "flipped": 0,
      "complexGeometry": false,
      "physicsEngine": 0,
      "colliderType": 0,
      "customColliders": [],
      "colliderVertices": [],
      "colliderIndicesFwd": [],
      "colliderIndicesBack": [],
      "colliderConvex": false,
      "colliderSmoothSphereCollisions": false,
      "polygonCollider2D": [],
      "edgeCollider2D": [],
      "attachPoints": []
    },
    {
      "name": "",
      "boundsData": [
        {
          "x": 31.0,
          "y": -31.0,
          "z": 0.0
        },
        {
          "x": 64.0,
          "y": 64.0,
          "z": 0.0
        }
      ],
      "untrimmedBoundsData": [
        {
          "x": 31.0,
          "y": -31.0,
          "z": 0.0
        },
        {
          "x": 64.0,
          "y": 64.0,
          "z": 0.0
        }
      ],
      "texelSize": {
        "x": 1.0,
        "y": 1.0
      },
      "positions": [
        {
          "x": -1.0,
          "y": -63.0,
          "z": 0.0
        },
        {
          "x": 63.0,
          "y": -63.0,
          "z": 0.0
        },
        {
          "x": -1.0,
          "y": 1.0,
          "z": 0.0
        },
        {
          "x": 63.0,
          "y": 1.0,
          "z": 0.0
        }
      ],
      "normals": [],
      "tangents": [],
      "uvs": [
        {
          "x": 0.0019541015,
          "y": 0.7910166
        },
        {
          "x": 0.0039052735,
          "y": 0.7910166
        },
        {
          "x": 0.0019541015,
          "y": 0.7929678
        },
        {
          "x": 0.0039052735,
          "y": 0.7929678
        }
      ],
      "normalizedUvs": [],
      "indices": [
        0,
        3,
        1,
        2,
        3,
        0
      ],
      "material": {
        "m_FileID": 0,
        "m_PathID": 85
      },
      "materialId": 0,
      "materialIndexData": [],
      "sourceTextureGUID": "",
      "extractRegion": false,
      "regionX": 0,
      "regionY": 0,
      "regionW": 0,
      "regionH": 0,
      "flipped": 0,
      "complexGeometry": false,
      "physicsEngine": 0,
      "colliderType": 0,
      "customColliders": [],
      "colliderVertices": [],
      "colliderIndicesFwd": [],
      "colliderIndicesBack": [],
      "colliderConvex": false,
      "colliderSmoothSphereCollisions": false,
      "polygonCollider2D": [],
      "edgeCollider2D": [],
      "attachPoints": []
    },
    {
      "name": "",
      "boundsData": [
        {
          "x": 31.0,
          "y": -31.0,
          "z": 0.0
        },
        {
          "x": 64.0,
          "y": 64.0,
          "z": 0.0
        }
      ],
      "untrimmedBoundsData": [
        {
          "x": 31.0,
          "y": -31.0,
          "z": 0.0
        },
        {
          "x": 64.0,
          "y": 64.0,
          "z": 0.0
        }
      ],
      "texelSize": {
        "x": 1.0,
        "y": 1.0
      },
      "positions": [
        {
          "x": -1.0,
          "y": -63.0,
          "z": 0.0
        },
        {
          "x": 63.0,
          "y": -63.0,
          "z": 0.0
        },
        {
          "x": -1.0,
          "y": 1.0,
          "z": 0.0
        },
        {
          "x": 63.0,
          "y": 1.0,
          "z": 0.0
        }
      ],
      "normals": [],
      "tangents": [],
      "uvs": [
        {
          "x": 0.0019541015,
          "y": 0.7910166
        },
        {
          "x": 0.0039052735,
          "y": 0.7910166
        },
        {
          "x": 0.0019541015,
          "y": 0.7929678
        },
        {
          "x": 0.0039052735,
          "y": 0.7929678
        }
      ],
      "normalizedUvs": [],
      "indices": [
        0,
        3,
        1,
        2,
        3,
        0
      ],
      "material": {
        "m_FileID": 0,
        "m_PathID": 85
      },
      "materialId": 0,
      "materialIndexData": [],
      "sourceTextureGUID": "",
      "extractRegion": false,
      "regionX": 0,
      "regionY": 0,
      "regionW": 0,
      "regionH": 0,
      "flipped": 0,
      "complexGeometry": false,
      "physicsEngine": 0,
      "colliderType": 0,
      "customColliders": [],
      "colliderVertices": [],
      "colliderIndicesFwd": [],
      "colliderIndicesBack": [],
      "colliderConvex": false,
      "colliderSmoothSphereCollisions": false,
      "polygonCollider2D": [],
      "edgeCollider2D": [],
      "attachPoints": []
    },
    {
      "name": "",
      "boundsData": [
        {
          "x": 31.0,
          "y": -31.0,
          "z": 0.0
        },
        {
          "x": 64.0,
          "y": 64.0,
          "z": 0.0
        }
      ],
      "untrimmedBoundsData": [
        {
          "x": 31.0,
          "y": -31.0,
          "z": 0.0
        },
        {
          "x": 64.0,
          "y": 64.0,
          "z": 0.0
        }
      ],
      "texelSize": {
        "x": 1.0,
        "y": 1.0
      },
      "positions": [
        {
          "x": -1.0,
          "y": -63.0,
          "z": 0.0
        },
        {
          "x": 63.0,
          "y": -63.0,
          "z": 0.0
        },
        {
          "x": -1.0,
          "y": 1.0,
          "z": 0.0
        },
        {
          "x": 63.0,
          "y": 1.0,
          "z": 0.0
        }
      ],
      "normals": [],
      "tangents": [],
      "uvs": [
        {
          "x": 0.0019541015,
          "y": 0.7910166
        },
        {
          "x": 0.0039052735,
          "y": 0.7910166
        },
        {
          "x": 0.0019541015,
          "y": 0.7929678
        },
        {
          "x": 0.0039052735,
          "y": 0.7929678
        }
      ],
      "normalizedUvs": [],
      "indices": [
        0,
        3,
        1,
        2,
        3,
        0
      ],
      "material": {
        "m_FileID": 0,
        "m_PathID": 85
      },
      "materialId": 0,
      "materialIndexData": [],
      "sourceTextureGUID": "",
      "extractRegion": false,
      "regionX": 0,
      "regionY": 0,
      "regionW": 0,
      "regionH": 0,
      "flipped": 0,
      "complexGeometry": false,
      "physicsEngine": 0,
      "colliderType": 0,
      "customColliders": [],
      "colliderVertices": [],
      "colliderIndicesFwd": [],
      "colliderIndicesBack": [],
      "colliderConvex": false,
      "colliderSmoothSphereCollisions": false,
      "polygonCollider2D": [],
      "edgeCollider2D": [],
      "attachPoints": []
    },
    {
      "name": "",
      "boundsData": [
        {
          "x": 31.0,
          "y": -31.0,
          "z": 0.0
        },
        {
          "x": 64.0,
          "y": 64.0,
          "z": 0.0
        }
      ],
      "untrimmedBoundsData": [
        {
          "x": 31.0,
          "y": -31.0,
          "z": 0.0
        },
        {
          "x": 64.0,
          "y": 64.0,
          "z": 0.0
        }
      ],
      "texelSize": {
        "x": 1.0,
        "y": 1.0
      },
      "positions": [
        {
          "x": -1.0,
          "y": -63.0,
          "z": 0.0
        },
        {
          "x": 63.0,
          "y": -63.0,
          "z": 0.0
        },
        {
          "x": -1.0,
          "y": 1.0,
          "z": 0.0
        },
        {
          "x": 63.0,
          "y": 1.0,
          "z": 0.0
        }
      ],
      "normals": [],
      "tangents": [],
      "uvs": [
        {
          "x": 0.0019541015,
          "y": 0.7910166
        },
        {
          "x": 0.0039052735,
          "y": 0.7910166
        },
        {
          "x": 0.0019541015,
          "y": 0.7929678
        },
        {
          "x": 0.0039052735,
          "y": 0.7929678
        }
      ],
      "normalizedUvs": [],
      "indices": [
        0,
        3,
        1,
        2,
        3,
        0
      ],
      "material": {
        "m_FileID": 0,
        "m_PathID": 85
      },
      "materialId": 0,
      "materialIndexData": [],
      "sourceTextureGUID": "",
      "extractRegion": false,
      "regionX": 0,
      "regionY": 0,
      "regionW": 0,
      "regionH": 0,
      "flipped": 0,
      "complexGeometry": false,
      "physicsEngine": 0,
      "colliderType": 0,
      "customColliders": [],
      "colliderVertices": [],
      "colliderIndicesFwd": [],
      "colliderIndicesBack": [],
      "colliderConvex": false,
      "colliderSmoothSphereCollisions": false,
      "polygonCollider2D": [],
      "edgeCollider2D": [],
      "attachPoints": []
    },
    {
      "name": "Fox_Trickster_A",
      "boundsData": [
        {
          "x": 0.0,
          "y": 0.0,
          "z": 0.0
        },
        {
          "x": 280.0,
          "y": 400.0,
          "z": 0.0
        }
      ],
      "untrimmedBoundsData": [
        {
          "x": 0.0,
          "y": 0.0,
          "z": 0.0
        },
        {
          "x": 280.0,
          "y": 400.0,
          "z": 0.0
        }
      ],
      "texelSize": {
        "x": 1.0,
        "y": 1.0
      },
      "positions": [
        {
          "x": -140.0,
          "y": -200.0,
          "z": 0.0
        },
        {
          "x": 140.0,
          "y": -200.0,
          "z": 0.0
        },
        {
          "x": -140.0,
          "y": 200.0,
          "z": 0.0
        },
        {
          "x": 140.0,
          "y": 200.0,
          "z": 0.0
        }
      ],
      "normals": [],
      "tangents": [],
      "uvs": [
        {
          "x": 0.0019541015,
          "y": 0.0019541015
        },
        {
          "x": 0.27538964,
          "y": 0.0019541015
        },
        {
          "x": 0.0019541015,
          "y": 0.39257714
        },
        {
          "x": 0.27538964,
          "y": 0.39257714
        }
      ],
      "normalizedUvs": [],
      "indices": [
        0,
        3,
        1,
        2,
        3,
        0
      ],
      "material": {
        "m_FileID": 0,
        "m_PathID": 85
      },
      "materialId": 0,
      "materialIndexData": [],
      "sourceTextureGUID": "c8b82c0b1365b47ab9868c03b4ad89ba",
      "extractRegion": false,
      "regionX": 0,
      "regionY": 0,
      "regionW": 0,
      "regionH": 0,
      "flipped": 0,
      "complexGeometry": false,
      "physicsEngine": 0,
      "colliderType": 1,
      "customColliders": [],
      "colliderVertices": [],
      "colliderIndicesFwd": [],
      "colliderIndicesBack": [],
      "colliderConvex": false,
      "colliderSmoothSphereCollisions": false,
      "polygonCollider2D": [],
      "edgeCollider2D": [],
      "attachPoints": []
    },
    {
      "name": "",
      "boundsData": [
        {
          "x": 31.0,
          "y": -31.0,
          "z": 0.0
        },
        {
          "x": 64.0,
          "y": 64.0,
          "z": 0.0
        }
      ],
      "untrimmedBoundsData": [
        {
          "x": 31.0,
          "y": -31.0,
          "z": 0.0
        },
        {
          "x": 64.0,
          "y": 64.0,
          "z": 0.0
        }
      ],
      "texelSize": {
        "x": 1.0,
        "y": 1.0
      },
      "positions": [
        {
          "x": -1.0,
          "y": -63.0,
          "z": 0.0
        },
        {
          "x": 63.0,
          "y": -63.0,
          "z": 0.0
        },
        {
          "x": -1.0,
          "y": 1.0,
          "z": 0.0
        },
        {
          "x": 63.0,
          "y": 1.0,
          "z": 0.0
        }
      ],
      "normals": [],
      "tangents": [],
      "uvs": [
        {
          "x": 0.0019541015,
          "y": 0.7910166
        },
        {
          "x": 0.0039052735,
          "y": 0.7910166
        },
        {
          "x": 0.0019541015,
          "y": 0.7929678
        },
        {
          "x": 0.0039052735,
          "y": 0.7929678
        }
      ],
      "normalizedUvs": [],
      "indices": [
        0,
        3,
        1,
        2,
        3,
        0
      ],
      "material": {
        "m_FileID": 0,
        "m_PathID": 85
      },
      "materialId": 0,
      "materialIndexData": [],
      "sourceTextureGUID": "",
      "extractRegion": false,
      "regionX": 0,
      "regionY": 0,
      "regionW": 0,
      "regionH": 0,
      "flipped": 0,
      "complexGeometry": false,
      "physicsEngine": 0,
      "colliderType": 0,
      "customColliders": [],
      "colliderVertices": [],
      "colliderIndicesFwd": [],
      "colliderIndicesBack": [],
      "colliderConvex": false,
      "colliderSmoothSphereCollisions": false,
      "polygonCollider2D": [],
      "edgeCollider2D": [],
      "attachPoints": []
    },
    {
      "name": "",
      "boundsData": [
        {
          "x": 31.0,
          "y": -31.0,
          "z": 0.0
        },
        {
          "x": 64.0,
          "y": 64.0,
          "z": 0.0
        }
      ],
      "untrimmedBoundsData": [
        {
          "x": 31.0,
          "y": -31.0,
          "z": 0.0
        },
        {
          "x": 64.0,
          "y": 64.0,
          "z": 0.0
        }
      ],
      "texelSize": {
        "x": 1.0,
        "y": 1.0
      },
      "positions": [
        {
          "x": -1.0,
          "y": -63.0,
          "z": 0.0
        },
        {
          "x": 63.0,
          "y": -63.0,
          "z": 0.0
        },
        {
          "x": -1.0,
          "y": 1.0,
          "z": 0.0
        },
        {
          "x": 63.0,
          "y": 1.0,
          "z": 0.0
        }
      ],
      "normals": [],
      "tangents": [],
      "uvs": [
        {
          "x": 0.0019541015,
          "y": 0.7910166
        },
        {
          "x": 0.0039052735,
          "y": 0.7910166
        },
        {
          "x": 0.0019541015,
          "y": 0.7929678
        },
        {
          "x": 0.0039052735,
          "y": 0.7929678
        }
      ],
      "normalizedUvs": [],
      "indices": [
        0,
        3,
        1,
        2,
        3,
        0
      ],
      "material": {
        "m_FileID": 0,
        "m_PathID": 85
      },
      "materialId": 0,
      "materialIndexData": [],
      "sourceTextureGUID": "",
      "extractRegion": false,
      "regionX": 0,
      "regionY": 0,
      "regionW": 0,
      "regionH": 0,
      "flipped": 0,
      "complexGeometry": false,
      "physicsEngine": 0,
      "colliderType": 0,
      "customColliders": [],
      "colliderVertices": [],
      "colliderIndicesFwd": [],
      "colliderIndicesBack": [],
      "colliderConvex": false,
      "colliderSmoothSphereCollisions": false,
      "polygonCollider2D": [],
      "edgeCollider2D": [],
      "attachPoints": []
    },
    {
      "name": "",
      "boundsData": [
        {
          "x": 31.0,
          "y": -31.0,
          "z": 0.0
        },
        {
          "x": 64.0,
          "y": 64.0,
          "z": 0.0
        }
      ],
      "untrimmedBoundsData": [
        {
          "x": 31.0,
          "y": -31.0,
          "z": 0.0
        },
        {
          "x": 64.0,
          "y": 64.0,
          "z": 0.0
        }
      ],
      "texelSize": {
        "x": 1.0,
        "y": 1.0
      },
      "positions": [
        {
          "x": -1.0,
          "y": -63.0,
          "z": 0.0
        },
        {
          "x": 63.0,
          "y": -63.0,
          "z": 0.0
        },
        {
          "x": -1.0,
          "y": 1.0,
          "z": 0.0
        },
        {
          "x": 63.0,
          "y": 1.0,
          "z": 0.0
        }
      ],
      "normals": [],
      "tangents": [],
      "uvs": [
        {
          "x": 0.0019541015,
          "y": 0.7910166
        },
        {
          "x": 0.0039052735,
          "y": 0.7910166
        },
        {
          "x": 0.0019541015,
          "y": 0.7929678
        },
        {
          "x": 0.0039052735,
          "y": 0.7929678
        }
      ],
      "normalizedUvs": [],
      "indices": [
        0,
        3,
        1,
        2,
        3,
        0
      ],
      "material": {
        "m_FileID": 0,
        "m_PathID": 85
      },
      "materialId": 0,
      "materialIndexData": [],
      "sourceTextureGUID": "",
      "extractRegion": false,
      "regionX": 0,
      "regionY": 0,
      "regionW": 0,
      "regionH": 0,
      "flipped": 0,
      "complexGeometry": false,
      "physicsEngine": 0,
      "colliderType": 0,
      "customColliders": [],
      "colliderVertices": [],
      "colliderIndicesFwd": [],
      "colliderIndicesBack": [],
      "colliderConvex": false,
      "colliderSmoothSphereCollisions": false,
      "polygonCollider2D": [],
      "edgeCollider2D": [],
      "attachPoints": []
    },
    {
      "name": "",
      "boundsData": [
        {
          "x": 31.0,
          "y": -31.0,
          "z": 0.0
        },
        {
          "x": 64.0,
          "y": 64.0,
          "z": 0.0
        }
      ],
      "untrimmedBoundsData": [
        {
          "x": 31.0,
          "y": -31.0,
          "z": 0.0
        },
        {
          "x": 64.0,
          "y": 64.0,
          "z": 0.0
        }
      ],
      "texelSize": {
        "x": 1.0,
        "y": 1.0
      },
      "positions": [
        {
          "x": -1.0,
          "y": -63.0,
          "z": 0.0
        },
        {
          "x": 63.0,
          "y": -63.0,
          "z": 0.0
        },
        {
          "x": -1.0,
          "y": 1.0,
          "z": 0.0
        },
        {
          "x": 63.0,
          "y": 1.0,
          "z": 0.0
        }
      ],
      "normals": [],
      "tangents": [],
      "uvs": [
        {
          "x": 0.0019541015,
          "y": 0.7910166
        },
        {
          "x": 0.0039052735,
          "y": 0.7910166
        },
        {
          "x": 0.0019541015,
          "y": 0.7929678
        },
        {
          "x": 0.0039052735,
          "y": 0.7929678
        }
      ],
      "normalizedUvs": [],
      "indices": [
        0,
        3,
        1,
        2,
        3,
        0
      ],
      "material": {
        "m_FileID": 0,
        "m_PathID": 85
      },
      "materialId": 0,
      "materialIndexData": [],
      "sourceTextureGUID": "",
      "extractRegion": false,
      "regionX": 0,
      "regionY": 0,
      "regionW": 0,
      "regionH": 0,
      "flipped": 0,
      "complexGeometry": false,
      "physicsEngine": 0,
      "colliderType": 0,
      "customColliders": [],
      "colliderVertices": [],
      "colliderIndicesFwd": [],
      "colliderIndicesBack": [],
      "colliderConvex": false,
      "colliderSmoothSphereCollisions": false,
      "polygonCollider2D": [],
      "edgeCollider2D": [],
      "attachPoints": []
    },
    {
      "name": "",
      "boundsData": [
        {
          "x": 31.0,
          "y": -31.0,
          "z": 0.0
        },
        {
          "x": 64.0,
          "y": 64.0,
          "z": 0.0
        }
      ],
      "untrimmedBoundsData": [
        {
          "x": 31.0,
          "y": -31.0,
          "z": 0.0
        },
        {
          "x": 64.0,
          "y": 64.0,
          "z": 0.0
        }
      ],
      "texelSize": {
        "x": 1.0,
        "y": 1.0
      },
      "positions": [
        {
          "x": -1.0,
          "y": -63.0,
          "z": 0.0
        },
        {
          "x": 63.0,
          "y": -63.0,
          "z": 0.0
        },
        {
          "x": -1.0,
          "y": 1.0,
          "z": 0.0
        },
        {
          "x": 63.0,
          "y": 1.0,
          "z": 0.0
        }
      ],
      "normals": [],
      "tangents": [],
      "uvs": [
        {
          "x": 0.0019541015,
          "y": 0.7910166
        },
        {
          "x": 0.0039052735,
          "y": 0.7910166
        },
        {
          "x": 0.0019541015,
          "y": 0.7929678
        },
        {
          "x": 0.0039052735,
          "y": 0.7929678
        }
      ],
      "normalizedUvs": [],
      "indices": [
        0,
        3,
        1,
        2,
        3,
        0
      ],
      "material": {
        "m_FileID": 0,
        "m_PathID": 85
      },
      "materialId": 0,
      "materialIndexData": [],
      "sourceTextureGUID": "",
      "extractRegion": false,
      "regionX": 0,
      "regionY": 0,
      "regionW": 0,
      "regionH": 0,
      "flipped": 0,
      "complexGeometry": false,
      "physicsEngine": 0,
      "colliderType": 0,
      "customColliders": [],
      "colliderVertices": [],
      "colliderIndicesFwd": [],
      "colliderIndicesBack": [],
      "colliderConvex": false,
      "colliderSmoothSphereCollisions": false,
      "polygonCollider2D": [],
      "edgeCollider2D": [],
      "attachPoints": []
    },
    {
      "name": "",
      "boundsData": [
        {
          "x": 31.0,
          "y": -31.0,
          "z": 0.0
        },
        {
          "x": 64.0,
          "y": 64.0,
          "z": 0.0
        }
      ],
      "untrimmedBoundsData": [
        {
          "x": 31.0,
          "y": -31.0,
          "z": 0.0
        },
        {
          "x": 64.0,
          "y": 64.0,
          "z": 0.0
        }
      ],
      "texelSize": {
        "x": 1.0,
        "y": 1.0
      },
      "positions": [
        {
          "x": -1.0,
          "y": -63.0,
          "z": 0.0
        },
        {
          "x": 63.0,
          "y": -63.0,
          "z": 0.0
        },
        {
          "x": -1.0,
          "y": 1.0,
          "z": 0.0
        },
        {
          "x": 63.0,
          "y": 1.0,
          "z": 0.0
        }
      ],
      "normals": [],
      "tangents": [],
      "uvs": [
        {
          "x": 0.0019541015,
          "y": 0.7910166
        },
        {
          "x": 0.0039052735,
          "y": 0.7910166
        },
        {
          "x": 0.0019541015,
          "y": 0.7929678
        },
        {
          "x": 0.0039052735,
          "y": 0.7929678
        }
      ],
      "normalizedUvs": [],
      "indices": [
        0,
        3,
        1,
        2,
        3,
        0
      ],
      "material": {
        "m_FileID": 0,
        "m_PathID": 85
      },
      "materialId": 0,
      "materialIndexData": [],
      "sourceTextureGUID": "",
      "extractRegion": false,
      "regionX": 0,
      "regionY": 0,
      "regionW": 0,
      "regionH": 0,
      "flipped": 0,
      "complexGeometry": false,
      "physicsEngine": 0,
      "colliderType": 0,
      "customColliders": [],
      "colliderVertices": [],
      "colliderIndicesFwd": [],
      "colliderIndicesBack": [],
      "colliderConvex": false,
      "colliderSmoothSphereCollisions": false,
      "polygonCollider2D": [],
      "edgeCollider2D": [],
      "attachPoints": []
    },
    {
      "name": "Flame_Spirit_A",
      "boundsData": [
        {
          "x": 0.0,
          "y": 0.0,
          "z": 0.0
        },
        {
          "x": 280.0,
          "y": 400.0,
          "z": 0.0
        }
      ],
      "untrimmedBoundsData": [
        {
          "x": 0.0,
          "y": 0.0,
          "z": 0.0
        },
        {
          "x": 280.0,
          "y": 400.0,
          "z": 0.0
        }
      ],
      "texelSize": {
        "x": 1.0,
        "y": 1.0
      },
      "positions": [
        {
          "x": -140.0,
          "y": -200.0,
          "z": 0.0
        },
        {
          "x": 140.0,
          "y": -200.0,
          "z": 0.0
        },
        {
          "x": -140.0,
          "y": 200.0,
          "z": 0.0
        },
        {
          "x": 140.0,
          "y": 200.0,
          "z": 0.0
        }
      ],
      "normals": [],
      "tangents": [],
      "uvs": [
        {
          "x": 0.0019541015,
          "y": 0.39648536
        },
        {
          "x": 0.27538964,
          "y": 0.39648536
        },
        {
          "x": 0.0019541015,
          "y": 0.7871084
        },
        {
          "x": 0.27538964,
          "y": 0.7871084
        }
      ],
      "normalizedUvs": [],
      "indices": [
        0,
        3,
        1,
        2,
        3,
        0
      ],
      "material": {
        "m_FileID": 0,
        "m_PathID": 85
      },
      "materialId": 0,
      "materialIndexData": [],
      "sourceTextureGUID": "dc0bf74757d53438198da3a0f11fec9d",
      "extractRegion": false,
      "regionX": 0,
      "regionY": 0,
      "regionW": 0,
      "regionH": 0,
      "flipped": 0,
      "complexGeometry": false,
      "physicsEngine": 0,
      "colliderType": 1,
      "customColliders": [],
      "colliderVertices": [],
      "colliderIndicesFwd": [],
      "colliderIndicesBack": [],
      "colliderConvex": false,
      "colliderSmoothSphereCollisions": false,
      "polygonCollider2D": [],
      "edgeCollider2D": [],
      "attachPoints": []
    },
    {
      "name": "",
      "boundsData": [
        {
          "x": 31.0,
          "y": -31.0,
          "z": 0.0
        },
        {
          "x": 64.0,
          "y": 64.0,
          "z": 0.0
        }
      ],
      "untrimmedBoundsData": [
        {
          "x": 31.0,
          "y": -31.0,
          "z": 0.0
        },
        {
          "x": 64.0,
          "y": 64.0,
          "z": 0.0
        }
      ],
      "texelSize": {
        "x": 1.0,
        "y": 1.0
      },
      "positions": [
        {
          "x": -1.0,
          "y": -63.0,
          "z": 0.0
        },
        {
          "x": 63.0,
          "y": -63.0,
          "z": 0.0
        },
        {
          "x": -1.0,
          "y": 1.0,
          "z": 0.0
        },
        {
          "x": 63.0,
          "y": 1.0,
          "z": 0.0
        }
      ],
      "normals": [],
      "tangents": [],
      "uvs": [
        {
          "x": 0.0019541015,
          "y": 0.7910166
        },
        {
          "x": 0.0039052735,
          "y": 0.7910166
        },
        {
          "x": 0.0019541015,
          "y": 0.7929678
        },
        {
          "x": 0.0039052735,
          "y": 0.7929678
        }
      ],
      "normalizedUvs": [],
      "indices": [
        0,
        3,
        1,
        2,
        3,
        0
      ],
      "material": {
        "m_FileID": 0,
        "m_PathID": 85
      },
      "materialId": 0,
      "materialIndexData": [],
      "sourceTextureGUID": "",
      "extractRegion": false,
      "regionX": 0,
      "regionY": 0,
      "regionW": 0,
      "regionH": 0,
      "flipped": 0,
      "complexGeometry": false,
      "physicsEngine": 0,
      "colliderType": 0,
      "customColliders": [],
      "colliderVertices": [],
      "colliderIndicesFwd": [],
      "colliderIndicesBack": [],
      "colliderConvex": false,
      "colliderSmoothSphereCollisions": false,
      "polygonCollider2D": [],
      "edgeCollider2D": [],
      "attachPoints": []
    },
    {
      "name": "",
      "boundsData": [
        {
          "x": 31.0,
          "y": -31.0,
          "z": 0.0
        },
        {
          "x": 64.0,
          "y": 64.0,
          "z": 0.0
        }
      ],
      "untrimmedBoundsData": [
        {
          "x": 31.0,
          "y": -31.0,
          "z": 0.0
        },
        {
          "x": 64.0,
          "y": 64.0,
          "z": 0.0
        }
      ],
      "texelSize": {
        "x": 1.0,
        "y": 1.0
      },
      "positions": [
        {
          "x": -1.0,
          "y": -63.0,
          "z": 0.0
        },
        {
          "x": 63.0,
          "y": -63.0,
          "z": 0.0
        },
        {
          "x": -1.0,
          "y": 1.0,
          "z": 0.0
        },
        {
          "x": 63.0,
          "y": 1.0,
          "z": 0.0
        }
      ],
      "normals": [],
      "tangents": [],
      "uvs": [
        {
          "x": 0.0019541015,
          "y": 0.7910166
        },
        {
          "x": 0.0039052735,
          "y": 0.7910166
        },
        {
          "x": 0.0019541015,
          "y": 0.7929678
        },
        {
          "x": 0.0039052735,
          "y": 0.7929678
        }
      ],
      "normalizedUvs": [],
      "indices": [
        0,
        3,
        1,
        2,
        3,
        0
      ],
      "material": {
        "m_FileID": 0,
        "m_PathID": 85
      },
      "materialId": 0,
      "materialIndexData": [],
      "sourceTextureGUID": "",
      "extractRegion": false,
      "regionX": 0,
      "regionY": 0,
      "regionW": 0,
      "regionH": 0,
      "flipped": 0,
      "complexGeometry": false,
      "physicsEngine": 0,
      "colliderType": 0,
      "customColliders": [],
      "colliderVertices": [],
      "colliderIndicesFwd": [],
      "colliderIndicesBack": [],
      "colliderConvex": false,
      "colliderSmoothSphereCollisions": false,
      "polygonCollider2D": [],
      "edgeCollider2D": [],
      "attachPoints": []
    },
    {
      "name": "",
      "boundsData": [
        {
          "x": 31.0,
          "y": -31.0,
          "z": 0.0
        },
        {
          "x": 64.0,
          "y": 64.0,
          "z": 0.0
        }
      ],
      "untrimmedBoundsData": [
        {
          "x": 31.0,
          "y": -31.0,
          "z": 0.0
        },
        {
          "x": 64.0,
          "y": 64.0,
          "z": 0.0
        }
      ],
      "texelSize": {
        "x": 1.0,
        "y": 1.0
      },
      "positions": [
        {
          "x": -1.0,
          "y": -63.0,
          "z": 0.0
        },
        {
          "x": 63.0,
          "y": -63.0,
          "z": 0.0
        },
        {
          "x": -1.0,
          "y": 1.0,
          "z": 0.0
        },
        {
          "x": 63.0,
          "y": 1.0,
          "z": 0.0
        }
      ],
      "normals": [],
      "tangents": [],
      "uvs": [
        {
          "x": 0.0019541015,
          "y": 0.7910166
        },
        {
          "x": 0.0039052735,
          "y": 0.7910166
        },
        {
          "x": 0.0019541015,
          "y": 0.7929678
        },
        {
          "x": 0.0039052735,
          "y": 0.7929678
        }
      ],
      "normalizedUvs": [],
      "indices": [
        0,
        3,
        1,
        2,
        3,
        0
      ],
      "material": {
        "m_FileID": 0,
        "m_PathID": 85
      },
      "materialId": 0,
      "materialIndexData": [],
      "sourceTextureGUID": "",
      "extractRegion": false,
      "regionX": 0,
      "regionY": 0,
      "regionW": 0,
      "regionH": 0,
      "flipped": 0,
      "complexGeometry": false,
      "physicsEngine": 0,
      "colliderType": 0,
      "customColliders": [],
      "colliderVertices": [],
      "colliderIndicesFwd": [],
      "colliderIndicesBack": [],
      "colliderConvex": false,
      "colliderSmoothSphereCollisions": false,
      "polygonCollider2D": [],
      "edgeCollider2D": [],
      "attachPoints": []
    },
    {
      "name": "",
      "boundsData": [
        {
          "x": 31.0,
          "y": -31.0,
          "z": 0.0
        },
        {
          "x": 64.0,
          "y": 64.0,
          "z": 0.0
        }
      ],
      "untrimmedBoundsData": [
        {
          "x": 31.0,
          "y": -31.0,
          "z": 0.0
        },
        {
          "x": 64.0,
          "y": 64.0,
          "z": 0.0
        }
      ],
      "texelSize": {
        "x": 1.0,
        "y": 1.0
      },
      "positions": [
        {
          "x": -1.0,
          "y": -63.0,
          "z": 0.0
        },
        {
          "x": 63.0,
          "y": -63.0,
          "z": 0.0
        },
        {
          "x": -1.0,
          "y": 1.0,
          "z": 0.0
        },
        {
          "x": 63.0,
          "y": 1.0,
          "z": 0.0
        }
      ],
      "normals": [],
      "tangents": [],
      "uvs": [
        {
          "x": 0.0019541015,
          "y": 0.7910166
        },
        {
          "x": 0.0039052735,
          "y": 0.7910166
        },
        {
          "x": 0.0019541015,
          "y": 0.7929678
        },
        {
          "x": 0.0039052735,
          "y": 0.7929678
        }
      ],
      "normalizedUvs": [],
      "indices": [
        0,
        3,
        1,
        2,
        3,
        0
      ],
      "material": {
        "m_FileID": 0,
        "m_PathID": 85
      },
      "materialId": 0,
      "materialIndexData": [],
      "sourceTextureGUID": "",
      "extractRegion": false,
      "regionX": 0,
      "regionY": 0,
      "regionW": 0,
      "regionH": 0,
      "flipped": 0,
      "complexGeometry": false,
      "physicsEngine": 0,
      "colliderType": 0,
      "customColliders": [],
      "colliderVertices": [],
      "colliderIndicesFwd": [],
      "colliderIndicesBack": [],
      "colliderConvex": false,
      "colliderSmoothSphereCollisions": false,
      "polygonCollider2D": [],
      "edgeCollider2D": [],
      "attachPoints": []
    },
    {
      "name": "",
      "boundsData": [
        {
          "x": 31.0,
          "y": -31.0,
          "z": 0.0
        },
        {
          "x": 64.0,
          "y": 64.0,
          "z": 0.0
        }
      ],
      "untrimmedBoundsData": [
        {
          "x": 31.0,
          "y": -31.0,
          "z": 0.0
        },
        {
          "x": 64.0,
          "y": 64.0,
          "z": 0.0
        }
      ],
      "texelSize": {
        "x": 1.0,
        "y": 1.0
      },
      "positions": [
        {
          "x": -1.0,
          "y": -63.0,
          "z": 0.0
        },
        {
          "x": 63.0,
          "y": -63.0,
          "z": 0.0
        },
        {
          "x": -1.0,
          "y": 1.0,
          "z": 0.0
        },
        {
          "x": 63.0,
          "y": 1.0,
          "z": 0.0
        }
      ],
      "normals": [],
      "tangents": [],
      "uvs": [
        {
          "x": 0.0019541015,
          "y": 0.7910166
        },
        {
          "x": 0.0039052735,
          "y": 0.7910166
        },
        {
          "x": 0.0019541015,
          "y": 0.7929678
        },
        {
          "x": 0.0039052735,
          "y": 0.7929678
        }
      ],
      "normalizedUvs": [],
      "indices": [
        0,
        3,
        1,
        2,
        3,
        0
      ],
      "material": {
        "m_FileID": 0,
        "m_PathID": 85
      },
      "materialId": 0,
      "materialIndexData": [],
      "sourceTextureGUID": "",
      "extractRegion": false,
      "regionX": 0,
      "regionY": 0,
      "regionW": 0,
      "regionH": 0,
      "flipped": 0,
      "complexGeometry": false,
      "physicsEngine": 0,
      "colliderType": 0,
      "customColliders": [],
      "colliderVertices": [],
      "colliderIndicesFwd": [],
      "colliderIndicesBack": [],
      "colliderConvex": false,
      "colliderSmoothSphereCollisions": false,
      "polygonCollider2D": [],
      "edgeCollider2D": [],
      "attachPoints": []
    },
    {
      "name": "",
      "boundsData": [
        {
          "x": 31.0,
          "y": -31.0,
          "z": 0.0
        },
        {
          "x": 64.0,
          "y": 64.0,
          "z": 0.0
        }
      ],
      "untrimmedBoundsData": [
        {
          "x": 31.0,
          "y": -31.0,
          "z": 0.0
        },
        {
          "x": 64.0,
          "y": 64.0,
          "z": 0.0
        }
      ],
      "texelSize": {
        "x": 1.0,
        "y": 1.0
      },
      "positions": [
        {
          "x": -1.0,
          "y": -63.0,
          "z": 0.0
        },
        {
          "x": 63.0,
          "y": -63.0,
          "z": 0.0
        },
        {
          "x": -1.0,
          "y": 1.0,
          "z": 0.0
        },
        {
          "x": 63.0,
          "y": 1.0,
          "z": 0.0
        }
      ],
      "normals": [],
      "tangents": [],
      "uvs": [
        {
          "x": 0.0019541015,
          "y": 0.7910166
        },
        {
          "x": 0.0039052735,
          "y": 0.7910166
        },
        {
          "x": 0.0019541015,
          "y": 0.7929678
        },
        {
          "x": 0.0039052735,
          "y": 0.7929678
        }
      ],
      "normalizedUvs": [],
      "indices": [
        0,
        3,
        1,
        2,
        3,
        0
      ],
      "material": {
        "m_FileID": 0,
        "m_PathID": 85
      },
      "materialId": 0,
      "materialIndexData": [],
      "sourceTextureGUID": "",
      "extractRegion": false,
      "regionX": 0,
      "regionY": 0,
      "regionW": 0,
      "regionH": 0,
      "flipped": 0,
      "complexGeometry": false,
      "physicsEngine": 0,
      "colliderType": 0,
      "customColliders": [],
      "colliderVertices": [],
      "colliderIndicesFwd": [],
      "colliderIndicesBack": [],
      "colliderConvex": false,
      "colliderSmoothSphereCollisions": false,
      "polygonCollider2D": [],
      "edgeCollider2D": [],
      "attachPoints": []
    },
    {
      "name": "",
      "boundsData": [
        {
          "x": 31.0,
          "y": -31.0,
          "z": 0.0
        },
        {
          "x": 64.0,
          "y": 64.0,
          "z": 0.0
        }
      ],
      "untrimmedBoundsData": [
        {
          "x": 31.0,
          "y": -31.0,
          "z": 0.0
        },
        {
          "x": 64.0,
          "y": 64.0,
          "z": 0.0
        }
      ],
      "texelSize": {
        "x": 1.0,
        "y": 1.0
      },
      "positions": [
        {
          "x": -1.0,
          "y": -63.0,
          "z": 0.0
        },
        {
          "x": 63.0,
          "y": -63.0,
          "z": 0.0
        },
        {
          "x": -1.0,
          "y": 1.0,
          "z": 0.0
        },
        {
          "x": 63.0,
          "y": 1.0,
          "z": 0.0
        }
      ],
      "normals": [],
      "tangents": [],
      "uvs": [
        {
          "x": 0.0019541015,
          "y": 0.7910166
        },
        {
          "x": 0.0039052735,
          "y": 0.7910166
        },
        {
          "x": 0.0019541015,
          "y": 0.7929678
        },
        {
          "x": 0.0039052735,
          "y": 0.7929678
        }
      ],
      "normalizedUvs": [],
      "indices": [
        0,
        3,
        1,
        2,
        3,
        0
      ],
      "material": {
        "m_FileID": 0,
        "m_PathID": 85
      },
      "materialId": 0,
      "materialIndexData": [],
      "sourceTextureGUID": "",
      "extractRegion": false,
      "regionX": 0,
      "regionY": 0,
      "regionW": 0,
      "regionH": 0,
      "flipped": 0,
      "complexGeometry": false,
      "physicsEngine": 0,
      "colliderType": 0,
      "customColliders": [],
      "colliderVertices": [],
      "colliderIndicesFwd": [],
      "colliderIndicesBack": [],
      "colliderConvex": false,
      "colliderSmoothSphereCollisions": false,
      "polygonCollider2D": [],
      "edgeCollider2D": [],
      "attachPoints": []
    },
    {
      "name": "Fire_Imp_A",
      "boundsData": [
        {
          "x": 0.0,
          "y": 0.0,
          "z": 0.0
        },
        {
          "x": 280.0,
          "y": 400.0,
          "z": 0.0
        }
      ],
      "untrimmedBoundsData": [
        {
          "x": 0.0,
          "y": 0.0,
          "z": 0.0
        },
        {
          "x": 280.0,
          "y": 400.0,
          "z": 0.0
        }
      ],
      "texelSize": {
        "x": 1.0,
        "y": 1.0
      },
      "positions": [
        {
          "x": -140.0,
          "y": -200.0,
          "z": 0.0
        },
        {
          "x": 140.0,
          "y": -200.0,
          "z": 0.0
        },
        {
          "x": -140.0,
          "y": 200.0,
          "z": 0.0
        },
        {
          "x": 140.0,
          "y": 200.0,
          "z": 0.0
        }
      ],
      "normals": [],
      "tangents": [],
      "uvs": [
        {
          "x": 0.27929786,
          "y": 0.0019541015
        },
        {
          "x": 0.27929786,
          "y": 0.27538964
        },
        {
          "x": 0.6699209,
          "y": 0.0019541015
        },
        {
          "x": 0.6699209,
          "y": 0.27538964
        }
      ],
      "normalizedUvs": [],
      "indices": [
        0,
        3,
        1,
        2,
        3,
        0
      ],
      "material": {
        "m_FileID": 0,
        "m_PathID": 85
      },
      "materialId": 0,
      "materialIndexData": [],
      "sourceTextureGUID": "e8903d4edd7d34948bde62e2ef81f84a",
      "extractRegion": false,
      "regionX": 0,
      "regionY": 0,
      "regionW": 0,
      "regionH": 0,
      "flipped": 1,
      "complexGeometry": false,
      "physicsEngine": 0,
      "colliderType": 1,
      "customColliders": [],
      "colliderVertices": [],
      "colliderIndicesFwd": [],
      "colliderIndicesBack": [],
      "colliderConvex": false,
      "colliderSmoothSphereCollisions": false,
      "polygonCollider2D": [],
      "edgeCollider2D": [],
      "attachPoints": []
    },
    {
      "name": "",
      "boundsData": [
        {
          "x": 31.0,
          "y": -31.0,
          "z": 0.0
        },
        {
          "x": 64.0,
          "y": 64.0,
          "z": 0.0
        }
      ],
      "untrimmedBoundsData": [
        {
          "x": 31.0,
          "y": -31.0,
          "z": 0.0
        },
        {
          "x": 64.0,
          "y": 64.0,
          "z": 0.0
        }
      ],
      "texelSize": {
        "x": 1.0,
        "y": 1.0
      },
      "positions": [
        {
          "x": -1.0,
          "y": -63.0,
          "z": 0.0
        },
        {
          "x": 63.0,
          "y": -63.0,
          "z": 0.0
        },
        {
          "x": -1.0,
          "y": 1.0,
          "z": 0.0
        },
        {
          "x": 63.0,
          "y": 1.0,
          "z": 0.0
        }
      ],
      "normals": [],
      "tangents": [],
      "uvs": [
        {
          "x": 0.0019541015,
          "y": 0.7910166
        },
        {
          "x": 0.0039052735,
          "y": 0.7910166
        },
        {
          "x": 0.0019541015,
          "y": 0.7929678
        },
        {
          "x": 0.0039052735,
          "y": 0.7929678
        }
      ],
      "normalizedUvs": [],
      "indices": [
        0,
        3,
        1,
        2,
        3,
        0
      ],
      "material": {
        "m_FileID": 0,
        "m_PathID": 85
      },
      "materialId": 0,
      "materialIndexData": [],
      "sourceTextureGUID": "",
      "extractRegion": false,
      "regionX": 0,
      "regionY": 0,
      "regionW": 0,
      "regionH": 0,
      "flipped": 0,
      "complexGeometry": false,
      "physicsEngine": 0,
      "colliderType": 0,
      "customColliders": [],
      "colliderVertices": [],
      "colliderIndicesFwd": [],
      "colliderIndicesBack": [],
      "colliderConvex": false,
      "colliderSmoothSphereCollisions": false,
      "polygonCollider2D": [],
      "edgeCollider2D": [],
      "attachPoints": []
    },
    {
      "name": "Druid_A",
      "boundsData": [
        {
          "x": 0.0,
          "y": 0.0,
          "z": 0.0
        },
        {
          "x": 280.0,
          "y": 400.0,
          "z": 0.0
        }
      ],
      "untrimmedBoundsData": [
        {
          "x": 0.0,
          "y": 0.0,
          "z": 0.0
        },
        {
          "x": 280.0,
          "y": 400.0,
          "z": 0.0
        }
      ],
      "texelSize": {
        "x": 1.0,
        "y": 1.0
      },
      "positions": [
        {
          "x": -140.0,
          "y": -200.0,
          "z": 0.0
        },
        {
          "x": 140.0,
          "y": -200.0,
          "z": 0.0
        },
        {
          "x": -140.0,
          "y": 200.0,
          "z": 0.0
        },
        {
          "x": 140.0,
          "y": 200.0,
          "z": 0.0
        }
      ],
      "normals": [],
      "tangents": [],
      "uvs": [
        {
          "x": 0.6738291,
          "y": 0.0019541015
        },
        {
          "x": 0.9472647,
          "y": 0.0019541015
        },
        {
          "x": 0.6738291,
          "y": 0.39257714
        },
        {
          "x": 0.9472647,
          "y": 0.39257714
        }
      ],
      "normalizedUvs": [],
      "indices": [
        0,
        3,
        1,
        2,
        3,
        0
      ],
      "material": {
        "m_FileID": 0,
        "m_PathID": 85
      },
      "materialId": 0,
      "materialIndexData": [],
      "sourceTextureGUID": "09a31d2530646424a833b8f3c613ace2",
      "extractRegion": false,
      "regionX": 0,
      "regionY": 0,
      "regionW": 0,
      "regionH": 0,
      "flipped": 0,
      "complexGeometry": false,
      "physicsEngine": 0,
      "colliderType": 1,
      "customColliders": [],
      "colliderVertices": [],
      "colliderIndicesFwd": [],
      "colliderIndicesBack": [],
      "colliderConvex": false,
      "colliderSmoothSphereCollisions": false,
      "polygonCollider2D": [],
      "edgeCollider2D": [],
      "attachPoints": []
    },
    {
      "name": "",
      "boundsData": [
        {
          "x": 31.0,
          "y": -31.0,
          "z": 0.0
        },
        {
          "x": 64.0,
          "y": 64.0,
          "z": 0.0
        }
      ],
      "untrimmedBoundsData": [
        {
          "x": 31.0,
          "y": -31.0,
          "z": 0.0
        },
        {
          "x": 64.0,
          "y": 64.0,
          "z": 0.0
        }
      ],
      "texelSize": {
        "x": 1.0,
        "y": 1.0
      },
      "positions": [
        {
          "x": -1.0,
          "y": -63.0,
          "z": 0.0
        },
        {
          "x": 63.0,
          "y": -63.0,
          "z": 0.0
        },
        {
          "x": -1.0,
          "y": 1.0,
          "z": 0.0
        },
        {
          "x": 63.0,
          "y": 1.0,
          "z": 0.0
        }
      ],
      "normals": [],
      "tangents": [],
      "uvs": [
        {
          "x": 0.0019541015,
          "y": 0.7910166
        },
        {
          "x": 0.0039052735,
          "y": 0.7910166
        },
        {
          "x": 0.0019541015,
          "y": 0.7929678
        },
        {
          "x": 0.0039052735,
          "y": 0.7929678
        }
      ],
      "normalizedUvs": [],
      "indices": [
        0,
        3,
        1,
        2,
        3,
        0
      ],
      "material": {
        "m_FileID": 0,
        "m_PathID": 85
      },
      "materialId": 0,
      "materialIndexData": [],
      "sourceTextureGUID": "",
      "extractRegion": false,
      "regionX": 0,
      "regionY": 0,
      "regionW": 0,
      "regionH": 0,
      "flipped": 0,
      "complexGeometry": false,
      "physicsEngine": 0,
      "colliderType": 0,
      "customColliders": [],
      "colliderVertices": [],
      "colliderIndicesFwd": [],
      "colliderIndicesBack": [],
      "colliderConvex": false,
      "colliderSmoothSphereCollisions": false,
      "polygonCollider2D": [],
      "edgeCollider2D": [],
      "attachPoints": []
    },
    {
      "name": "",
      "boundsData": [
        {
          "x": 31.0,
          "y": -31.0,
          "z": 0.0
        },
        {
          "x": 64.0,
          "y": 64.0,
          "z": 0.0
        }
      ],
      "untrimmedBoundsData": [
        {
          "x": 31.0,
          "y": -31.0,
          "z": 0.0
        },
        {
          "x": 64.0,
          "y": 64.0,
          "z": 0.0
        }
      ],
      "texelSize": {
        "x": 1.0,
        "y": 1.0
      },
      "positions": [
        {
          "x": -1.0,
          "y": -63.0,
          "z": 0.0
        },
        {
          "x": 63.0,
          "y": -63.0,
          "z": 0.0
        },
        {
          "x": -1.0,
          "y": 1.0,
          "z": 0.0
        },
        {
          "x": 63.0,
          "y": 1.0,
          "z": 0.0
        }
      ],
      "normals": [],
      "tangents": [],
      "uvs": [
        {
          "x": 0.0019541015,
          "y": 0.7910166
        },
        {
          "x": 0.0039052735,
          "y": 0.7910166
        },
        {
          "x": 0.0019541015,
          "y": 0.7929678
        },
        {
          "x": 0.0039052735,
          "y": 0.7929678
        }
      ],
      "normalizedUvs": [],
      "indices": [
        0,
        3,
        1,
        2,
        3,
        0
      ],
      "material": {
        "m_FileID": 0,
        "m_PathID": 85
      },
      "materialId": 0,
      "materialIndexData": [],
      "sourceTextureGUID": "",
      "extractRegion": false,
      "regionX": 0,
      "regionY": 0,
      "regionW": 0,
      "regionH": 0,
      "flipped": 0,
      "complexGeometry": false,
      "physicsEngine": 0,
      "colliderType": 0,
      "customColliders": [],
      "colliderVertices": [],
      "colliderIndicesFwd": [],
      "colliderIndicesBack": [],
      "colliderConvex": false,
      "colliderSmoothSphereCollisions": false,
      "polygonCollider2D": [],
      "edgeCollider2D": [],
      "attachPoints": []
    },
    {
      "name": "",
      "boundsData": [
        {
          "x": 31.0,
          "y": -31.0,
          "z": 0.0
        },
        {
          "x": 64.0,
          "y": 64.0,
          "z": 0.0
        }
      ],
      "untrimmedBoundsData": [
        {
          "x": 31.0,
          "y": -31.0,
          "z": 0.0
        },
        {
          "x": 64.0,
          "y": 64.0,
          "z": 0.0
        }
      ],
      "texelSize": {
        "x": 1.0,
        "y": 1.0
      },
      "positions": [
        {
          "x": -1.0,
          "y": -63.0,
          "z": 0.0
        },
        {
          "x": 63.0,
          "y": -63.0,
          "z": 0.0
        },
        {
          "x": -1.0,
          "y": 1.0,
          "z": 0.0
        },
        {
          "x": 63.0,
          "y": 1.0,
          "z": 0.0
        }
      ],
      "normals": [],
      "tangents": [],
      "uvs": [
        {
          "x": 0.0019541015,
          "y": 0.7910166
        },
        {
          "x": 0.0039052735,
          "y": 0.7910166
        },
        {
          "x": 0.0019541015,
          "y": 0.7929678
        },
        {
          "x": 0.0039052735,
          "y": 0.7929678
        }
      ],
      "normalizedUvs": [],
      "indices": [
        0,
        3,
        1,
        2,
        3,
        0
      ],
      "material": {
        "m_FileID": 0,
        "m_PathID": 85
      },
      "materialId": 0,
      "materialIndexData": [],
      "sourceTextureGUID": "",
      "extractRegion": false,
      "regionX": 0,
      "regionY": 0,
      "regionW": 0,
      "regionH": 0,
      "flipped": 0,
      "complexGeometry": false,
      "physicsEngine": 0,
      "colliderType": 0,
      "customColliders": [],
      "colliderVertices": [],
      "colliderIndicesFwd": [],
      "colliderIndicesBack": [],
      "colliderConvex": false,
      "colliderSmoothSphereCollisions": false,
      "polygonCollider2D": [],
      "edgeCollider2D": [],
      "attachPoints": []
    },
    {
      "name": "",
      "boundsData": [
        {
          "x": 31.0,
          "y": -31.0,
          "z": 0.0
        },
        {
          "x": 64.0,
          "y": 64.0,
          "z": 0.0
        }
      ],
      "untrimmedBoundsData": [
        {
          "x": 31.0,
          "y": -31.0,
          "z": 0.0
        },
        {
          "x": 64.0,
          "y": 64.0,
          "z": 0.0
        }
      ],
      "texelSize": {
        "x": 1.0,
        "y": 1.0
      },
      "positions": [
        {
          "x": -1.0,
          "y": -63.0,
          "z": 0.0
        },
        {
          "x": 63.0,
          "y": -63.0,
          "z": 0.0
        },
        {
          "x": -1.0,
          "y": 1.0,
          "z": 0.0
        },
        {
          "x": 63.0,
          "y": 1.0,
          "z": 0.0
        }
      ],
      "normals": [],
      "tangents": [],
      "uvs": [
        {
          "x": 0.0019541015,
          "y": 0.7910166
        },
        {
          "x": 0.0039052735,
          "y": 0.7910166
        },
        {
          "x": 0.0019541015,
          "y": 0.7929678
        },
        {
          "x": 0.0039052735,
          "y": 0.7929678
        }
      ],
      "normalizedUvs": [],
      "indices": [
        0,
        3,
        1,
        2,
        3,
        0
      ],
      "material": {
        "m_FileID": 0,
        "m_PathID": 85
      },
      "materialId": 0,
      "materialIndexData": [],
      "sourceTextureGUID": "",
      "extractRegion": false,
      "regionX": 0,
      "regionY": 0,
      "regionW": 0,
      "regionH": 0,
      "flipped": 0,
      "complexGeometry": false,
      "physicsEngine": 0,
      "colliderType": 0,
      "customColliders": [],
      "colliderVertices": [],
      "colliderIndicesFwd": [],
      "colliderIndicesBack": [],
      "colliderConvex": false,
      "colliderSmoothSphereCollisions": false,
      "polygonCollider2D": [],
      "edgeCollider2D": [],
      "attachPoints": []
    },
    {
      "name": "",
      "boundsData": [
        {
          "x": 31.0,
          "y": -31.0,
          "z": 0.0
        },
        {
          "x": 64.0,
          "y": 64.0,
          "z": 0.0
        }
      ],
      "untrimmedBoundsData": [
        {
          "x": 31.0,
          "y": -31.0,
          "z": 0.0
        },
        {
          "x": 64.0,
          "y": 64.0,
          "z": 0.0
        }
      ],
      "texelSize": {
        "x": 1.0,
        "y": 1.0
      },
      "positions": [
        {
          "x": -1.0,
          "y": -63.0,
          "z": 0.0
        },
        {
          "x": 63.0,
          "y": -63.0,
          "z": 0.0
        },
        {
          "x": -1.0,
          "y": 1.0,
          "z": 0.0
        },
        {
          "x": 63.0,
          "y": 1.0,
          "z": 0.0
        }
      ],
      "normals": [],
      "tangents": [],
      "uvs": [
        {
          "x": 0.0019541015,
          "y": 0.7910166
        },
        {
          "x": 0.0039052735,
          "y": 0.7910166
        },
        {
          "x": 0.0019541015,
          "y": 0.7929678
        },
        {
          "x": 0.0039052735,
          "y": 0.7929678
        }
      ],
      "normalizedUvs": [],
      "indices": [
        0,
        3,
        1,
        2,
        3,
        0
      ],
      "material": {
        "m_FileID": 0,
        "m_PathID": 85
      },
      "materialId": 0,
      "materialIndexData": [],
      "sourceTextureGUID": "",
      "extractRegion": false,
      "regionX": 0,
      "regionY": 0,
      "regionW": 0,
      "regionH": 0,
      "flipped": 0,
      "complexGeometry": false,
      "physicsEngine": 0,
      "colliderType": 0,
      "customColliders": [],
      "colliderVertices": [],
      "colliderIndicesFwd": [],
      "colliderIndicesBack": [],
      "colliderConvex": false,
      "colliderSmoothSphereCollisions": false,
      "polygonCollider2D": [],
      "edgeCollider2D": [],
      "attachPoints": []
    },
    {
      "name": "Earth_Elemental_A",
      "boundsData": [
        {
          "x": 0.0,
          "y": 0.0,
          "z": 0.0
        },
        {
          "x": 280.0,
          "y": 400.0,
          "z": 0.0
        }
      ],
      "untrimmedBoundsData": [
        {
          "x": 0.0,
          "y": 0.0,
          "z": 0.0
        },
        {
          "x": 280.0,
          "y": 400.0,
          "z": 0.0
        }
      ],
      "texelSize": {
        "x": 1.0,
        "y": 1.0
      },
      "positions": [
        {
          "x": -140.0,
          "y": -200.0,
          "z": 0.0
        },
        {
          "x": 140.0,
          "y": -200.0,
          "z": 0.0
        },
        {
          "x": -140.0,
          "y": 200.0,
          "z": 0.0
        },
        {
          "x": 140.0,
          "y": 200.0,
          "z": 0.0
        }
      ],
      "normals": [],
      "tangents": [],
      "uvs": [
        {
          "x": 0.27929786,
          "y": 0.27929786
        },
        {
          "x": 0.27929786,
          "y": 0.5527334
        },
        {
          "x": 0.6699209,
          "y": 0.27929786
        },
        {
          "x": 0.6699209,
          "y": 0.5527334
        }
      ],
      "normalizedUvs": [],
      "indices": [
        0,
        3,
        1,
        2,
        3,
        0
      ],
      "material": {
        "m_FileID": 0,
        "m_PathID": 85
      },
      "materialId": 0,
      "materialIndexData": [],
      "sourceTextureGUID": "4caa9e4c7e6a143c48d5cad3f262d8aa",
      "extractRegion": false,
      "regionX": 0,
      "regionY": 0,
      "regionW": 0,
      "regionH": 0,
      "flipped": 1,
      "complexGeometry": false,
      "physicsEngine": 0,
      "colliderType": 1,
      "customColliders": [],
      "colliderVertices": [],
      "colliderIndicesFwd": [],
      "colliderIndicesBack": [],
      "colliderConvex": false,
      "colliderSmoothSphereCollisions": false,
      "polygonCollider2D": [],
      "edgeCollider2D": [],
      "attachPoints": []
    },
    {
      "name": "",
      "boundsData": [
        {
          "x": 31.0,
          "y": -31.0,
          "z": 0.0
        },
        {
          "x": 64.0,
          "y": 64.0,
          "z": 0.0
        }
      ],
      "untrimmedBoundsData": [
        {
          "x": 31.0,
          "y": -31.0,
          "z": 0.0
        },
        {
          "x": 64.0,
          "y": 64.0,
          "z": 0.0
        }
      ],
      "texelSize": {
        "x": 1.0,
        "y": 1.0
      },
      "positions": [
        {
          "x": -1.0,
          "y": -63.0,
          "z": 0.0
        },
        {
          "x": 63.0,
          "y": -63.0,
          "z": 0.0
        },
        {
          "x": -1.0,
          "y": 1.0,
          "z": 0.0
        },
        {
          "x": 63.0,
          "y": 1.0,
          "z": 0.0
        }
      ],
      "normals": [],
      "tangents": [],
      "uvs": [
        {
          "x": 0.0019541015,
          "y": 0.7910166
        },
        {
          "x": 0.0039052735,
          "y": 0.7910166
        },
        {
          "x": 0.0019541015,
          "y": 0.7929678
        },
        {
          "x": 0.0039052735,
          "y": 0.7929678
        }
      ],
      "normalizedUvs": [],
      "indices": [
        0,
        3,
        1,
        2,
        3,
        0
      ],
      "material": {
        "m_FileID": 0,
        "m_PathID": 85
      },
      "materialId": 0,
      "materialIndexData": [],
      "sourceTextureGUID": "",
      "extractRegion": false,
      "regionX": 0,
      "regionY": 0,
      "regionW": 0,
      "regionH": 0,
      "flipped": 0,
      "complexGeometry": false,
      "physicsEngine": 0,
      "colliderType": 0,
      "customColliders": [],
      "colliderVertices": [],
      "colliderIndicesFwd": [],
      "colliderIndicesBack": [],
      "colliderConvex": false,
      "colliderSmoothSphereCollisions": false,
      "polygonCollider2D": [],
      "edgeCollider2D": [],
      "attachPoints": []
    },
    {
      "name": "Forest_Beast_A",
      "boundsData": [
        {
          "x": 0.0,
          "y": 0.0,
          "z": 0.0
        },
        {
          "x": 280.0,
          "y": 400.0,
          "z": 0.0
        }
      ],
      "untrimmedBoundsData": [
        {
          "x": 0.0,
          "y": 0.0,
          "z": 0.0
        },
        {
          "x": 280.0,
          "y": 400.0,
          "z": 0.0
        }
      ],
      "texelSize": {
        "x": 1.0,
        "y": 1.0
      },
      "positions": [
        {
          "x": -140.0,
          "y": -200.0,
          "z": 0.0
        },
        {
          "x": 140.0,
          "y": -200.0,
          "z": 0.0
        },
        {
          "x": -140.0,
          "y": 200.0,
          "z": 0.0
        },
        {
          "x": 140.0,
          "y": 200.0,
          "z": 0.0
        }
      ],
      "normals": [],
      "tangents": [],
      "uvs": [
        {
          "x": 0.6738291,
          "y": 0.39648536
        },
        {
          "x": 0.9472647,
          "y": 0.39648536
        },
        {
          "x": 0.6738291,
          "y": 0.7871084
        },
        {
          "x": 0.9472647,
          "y": 0.7871084
        }
      ],
      "normalizedUvs": [],
      "indices": [
        0,
        3,
        1,
        2,
        3,
        0
      ],
      "material": {
        "m_FileID": 0,
        "m_PathID": 85
      },
      "materialId": 0,
      "materialIndexData": [],
      "sourceTextureGUID": "4d2ee63f2f46640d8b6eaf29a3812242",
      "extractRegion": false,
      "regionX": 0,
      "regionY": 0,
      "regionW": 0,
      "regionH": 0,
      "flipped": 0,
      "complexGeometry": false,
      "physicsEngine": 0,
      "colliderType": 1,
      "customColliders": [],
      "colliderVertices": [],
      "colliderIndicesFwd": [],
      "colliderIndicesBack": [],
      "colliderConvex": false,
      "colliderSmoothSphereCollisions": false,
      "polygonCollider2D": [],
      "edgeCollider2D": [],
      "attachPoints": []
    },
    {
      "name": "Fairy_A",
      "boundsData": [
        {
          "x": 0.0,
          "y": 0.0,
          "z": 0.0
        },
        {
          "x": 280.0,
          "y": 400.0,
          "z": 0.0
        }
      ],
      "untrimmedBoundsData": [
        {
          "x": 0.0,
          "y": 0.0,
          "z": 0.0
        },
        {
          "x": 280.0,
          "y": 400.0,
          "z": 0.0
        }
      ],
      "texelSize": {
        "x": 1.0,
        "y": 1.0
      },
      "positions": [
        {
          "x": -140.0,
          "y": -200.0,
          "z": 0.0
        },
        {
          "x": 140.0,
          "y": -200.0,
          "z": 0.0
        },
        {
          "x": -140.0,
          "y": 200.0,
          "z": 0.0
        },
        {
          "x": 140.0,
          "y": 200.0,
          "z": 0.0
        }
      ],
      "normals": [],
      "tangents": [],
      "uvs": [
        {
          "x": 0.27929786,
          "y": 0.5566416
        },
        {
          "x": 0.27929786,
          "y": 0.8300772
        },
        {
          "x": 0.6699209,
          "y": 0.5566416
        },
        {
          "x": 0.6699209,
          "y": 0.8300772
        }
      ],
      "normalizedUvs": [],
      "indices": [
        0,
        3,
        1,
        2,
        3,
        0
      ],
      "material": {
        "m_FileID": 0,
        "m_PathID": 85
      },
      "materialId": 0,
      "materialIndexData": [],
      "sourceTextureGUID": "a0c7cd307426743bd8ee7c7ab498cc21",
      "extractRegion": false,
      "regionX": 0,
      "regionY": 0,
      "regionW": 0,
      "regionH": 0,
      "flipped": 1,
      "complexGeometry": false,
      "physicsEngine": 0,
      "colliderType": 1,
      "customColliders": [],
      "colliderVertices": [],
      "colliderIndicesFwd": [],
      "colliderIndicesBack": [],
      "colliderConvex": false,
      "colliderSmoothSphereCollisions": false,
      "polygonCollider2D": [],
      "edgeCollider2D": [],
      "attachPoints": []
    }
  ],
  "premultipliedAlpha": false,
  "material": {
    "m_FileID": 0,
    "m_PathID": 0
  },
  "materials": [
    {
      "m_FileID": 0,
      "m_PathID": 85
    }
  ],
  "textures": [
    {
      "m_FileID": 0,
      "m_PathID": 439
    }
  ],
  "pngTextures": [],
  "materialPngTextureId": [],
  "textureFilterMode": 1,
  "textureMipMaps": false,
  "allowMultipleAtlases": false,
  "spriteCollectionGUID": "dee4a06a6636f439eb15932ac8431f61",
  "spriteCollectionName": "FirstTimeUserCardSet 2@1x",
  "assetName": "FirstTimeUserCardSet",
  "loadable": true,
  "invOrthoSize": 2.0,
  "halfTargetHeight": 0.5,
  "buildKey": 256879601,
  "dataGuid": "f2241ce91d70044169ccd7275821de86",
  "managedSpriteCollection": true,
  "hasPlatformData": false,
  "spriteCollectionPlatforms": [],
  "spriteCollectionPlatformGUIDs": []
}